[
  {
    "key": "switcher",
    "typeName": "表格"
  }, {
    "key": "user",
    "typeName": "个人中心"
  }, {
    "key": "dot-chart",
    "typeName": "数学图形"
  }, {
    "typeName": "D3.js图库",
    "key": "charts",
    "child": [
      {
        "name": "D3 简单柱状图",
        "key": "simple-bar-chart"
      },
      {
        "type": "charts",
        "key": "simple-bar-chart",
        "name": "D3 简单柱状图"
      },
      {
        "key": "simple-area-chart",
        "name": "D3 简单面积图"
      },
      {
        "key": "simple-bar-chart",
        "name": "D3 简单饼图、圆环图"
      },
      {
        "key": "simple-bar-chart",
        "name": "D3 简单线状图"
      }
    ]
  }
]